squaad/__init__.py
squaad/db.py
squaad/db_lite.py
squaad/file.py
squaad/git_local.py
squaad/ml.py
squaad/stats.py
squaad/sql/compilation.sql
squaad/sql/compilation_affiliation.sql
squaad/sql/developerMap.sql
squaad/sql/increase_decrease_affiliation.sql
squaad/sql/increase_decrease_query.sql
squaad/sql/quality_compilation.sql
squaad/sql/quality_compilation_commit_level.sql
squaad/sql/quality_difference_commit_level.sql
squaad-2.1.dist-info/LICENSE
squaad-2.1.dist-info/METADATA
squaad-2.1.dist-info/WHEEL
squaad-2.1.dist-info/top_level.txt
squaad-2.1.dist-info/RECORD
