Metadata-Version: 2.1
Name: squaad
Version: 2.1
Summary: Helper functions for running queries, ml pipeline, statistical analysis on SQUAAD framework
Home-page: http://github.com/fostiropoulos/squaad
Author: Iordanis Fostiropoulos
Author-email: danny.fostiropoulos@gmail.com
License: UNKNOWN
Platform: UNKNOWN
Classifier: Programming Language :: Python :: 3
Classifier: License :: OSI Approved :: Mozilla Public License 2.0 (MPL 2.0)
Classifier: Operating System :: OS Independent
Requires-Dist: psycopg2-binary
Requires-Dist: xlwt
Requires-Dist: GitPython
Requires-Dist: SQLAlchemy
Requires-Dist: imbalanced-learn
Requires-Dist: imblearn
Requires-Dist: matplotlib
Requires-Dist: numpy
Requires-Dist: pandas
Requires-Dist: python-dateutil
Requires-Dist: scipy
Requires-Dist: seaborn
Requires-Dist: sklearn
